{
  "health_potion": {
    "name": "Health Potion",
    "description": "A potion that restores a character's health points (HP).",
    "hp_restore": 50,
    "mp_restore": 0,
    "price": 50
  },
  "mana_potion": {
    "name": "Mana Potion",
    "description": "A potion that restores a character's magic points (MP) or other resource used for casting spells or abilities.",
    "hp_restore": 0,
    "mp_restore": 50,
    "price": 50
  },
  "elixir": {
    "name": "Elixir",
    "description": "A powerful potion that restores both HP and MP, often used in dire situations.",
    "hp_restore": 100,
    "mp_restore": 100,
    "price": 1000
  },
  "antidote": {
    "name": "Antidote",
    "description": "An item that cures poison or other status ailments that affect a character's performance in battle.",
    "hp_restore": 0,
    "mp_restore": 0,
    "cure_poison": true,
    "price": 50
  },
  "ether": {
    "name": "Ether",
    "description": "A special item that restores a character's MP or other resource over time, instead of all at once like a potion.",
    "hp_restore": 0,
    "mp_restore": 50,
    "over_time": true,
    "time_duration": 10,
    "price": 100
  },
  "phoenix_down": {
    "name": "Phoenix Down",
    "description": "An item that revives a fallen character with a small amount of HP, allowing them to rejoin the battle.",
    "hp_restore": 25,
    "mp_restore": 0,
    "revive": true,
    "price": 500
  },
  "invisibility_potion": {
    "name": "Potion of Invisibility",
    "description": "An item that makes a character invisible for a period of time, allowing them to avoid enemy encounters or sneak past obstacles.",
    "hp_restore": 0,
    "mp_restore": 0,
    "invisibility": true,
    "time_duration": 20,
    "price": 200
  },
  "fireball_scroll": {
    "name": "Scroll of Fireball",
    "description": "A one-time use item that casts a powerful fireball spell, dealing heavy damage to enemies in an area of effect.",
    "hp_restore": 0,
    "mp_restore": 20,
    "damage": 100,
    "area_of_effect": true,
    "price": 500
  },
  "grappling_hook": {
    "name": "Grappling Hook",
    "description": "An item that can be used to climb walls or reach high places, allowing characters to access new areas or shortcuts.",
    "hp_restore": 0,
    "mp_restore": 0,
    "grapple": true,
    "price": 100
  },
  "lockpick": {
    "name": "Lockpick",
    "description": "An item that allows characters to open locked doors or chests, potentially revealing valuable treasure or secrets.",
    "hp_restore": 0,
    "mp_restore": 0,
    "unlock": true,
    "price": 50
  }
}
